pd9530.py
pd9530-1.0.3.dist-info/DESCRIPTION.rst
pd9530-1.0.3.dist-info/METADATA
pd9530-1.0.3.dist-info/metadata.json
pd9530-1.0.3.dist-info/RECORD
pd9530-1.0.3.dist-info/top_level.txt
pd9530-1.0.3.dist-info/WHEEL
