Metadata-Version: 2.0
Name: pd9530
Version: 1.0.3
Summary: Library to interact with a PD9530 handheld scanner
Home-page: http://github.com/jokey2k/PD9530
Author: Markus Ullmann
Author-email: mail@markus-ullmann.de
License: BSD-3
Keywords: scanner,windows,usb,handheld
Platform: UNKNOWN
Classifier: Development Status :: 5 - Production/Stable
Classifier: Environment :: Console
Classifier: Environment :: Handhelds/PDA's
Classifier: Environment :: Other Environment
Classifier: Environment :: Plugins
Classifier: Environment :: Win32 (MS Windows)
Classifier: Intended Audience :: Customer Service
Classifier: Intended Audience :: Developers
Classifier: Intended Audience :: End Users/Desktop
Classifier: Intended Audience :: Manufacturing
Classifier: License :: OSI Approved :: BSD License
Classifier: Operating System :: Microsoft :: Windows :: Windows 7
Classifier: Operating System :: Microsoft :: Windows :: Windows Server 2003
Classifier: Operating System :: Microsoft :: Windows :: Windows Server 2008
Classifier: Operating System :: Microsoft :: Windows :: Windows XP
Classifier: Operating System :: POSIX :: Linux
Classifier: Operating System :: Unix
Classifier: Programming Language :: Python
Classifier: Programming Language :: Python :: 3.4
Classifier: Programming Language :: Python :: 3.5
Classifier: Programming Language :: Python :: 3 :: Only
Classifier: Topic :: Home Automation
Classifier: Topic :: Multimedia :: Graphics :: Capture :: Scanners
Classifier: Topic :: Office/Business :: Financial :: Point-Of-Sale
Classifier: Topic :: Software Development :: Libraries :: Python Modules
Classifier: Topic :: Terminals :: Serial
Classifier: Topic :: Utilities
Requires-Dist: pyserial
Provides-Extra: sendkeys
Requires-Dist: pywin32; extra == 'sendkeys'
